algebrix/__init__.py
algebrix/matrix/__init__.py
algebrix/matrix/matrix.py
algebrix/matrix/operations.py
algebrix/vector/__init__.py
algebrix/vector/operations.py
algebrix/vector/vector.py
algebrix-1.0.1.dist-info/licenses/LICENSE.txt
algebrix-1.0.1.dist-info/METADATA
algebrix-1.0.1.dist-info/WHEEL
algebrix-1.0.1.dist-info/top_level.txt
algebrix-1.0.1.dist-info/RECORD
