Metadata-Version: 2.4
Name: algebrix
Version: 1.0.1
Summary: Linear algebra on Python — вектора, матрицы, разложения
Author-email: Vlasov Artyom <t0mi.v@yandex.ru>
License-Expression: MIT
Project-URL: Homepage, https://github.com/Artemiadze/algebrix
Requires-Python: >=3.10
License-File: LICENSE.txt
Dynamic: license-file
